{
  "bo_params": {
    "temp": {
      "logbounds": [-10.0, -0.0],
      "candidates": [1e-3, 1e-6]
    },
    "sigma": {
      "logbounds": [-10.0, -0.0],
      "candidates": [1e-1, 1e-6]
    }
  },
  "run_params": {
    "img": 0,
    "num_iter": 50000,
    "lr": 1e-3,
    "seed": 1,
    "p_sigma": 0.1,
    "input_depth": 16,
    "show_every": 100,
    "plot": true,
    "save": true,
    "devices": ["cuda:2", "cuda:3"],
    "save_path": "/media/laves/bo_logs_mfvi_den",
    "bo_results_path": "/media/laves/bo_results_mfvi_den"
  }
}
